{
	"version": "choo server v1",




"admobbannerId": "",
	"admobInterId": "",
	"admobReward": "",
		"appopen": "",

"applovinsdk": "RJ8mZelv26OxA43ll2MRxm8v8aNAosI0XTA6JISKRJuTuJs9PKCI_TxwoatxwbKJ4LtuTbrxRSvGZuBg6InDAB",
"applovinbanner": "691f119ec70b12eb",
"applovininter": "f4db500ea252c538",
"applovinreward": "2efdfd572a23ca24",

"adscounter": "0",

"adsSwitchInter details ": "0 auto 1 admob 2 applovin",

"adsSwitchInter": "2",
"adsSwitchBanner": "2",
"adsSwitchReward": "2"
	





}
